LICENSE
jobmanager/__init__.py
jobmanager/clients.py
jobmanager/jobmanager.py
jobmanager/ode_wrapper.py
jobmanager/servers.py
jobmanager/signalDelay.py
jobmanager-0.4.8.dist-info/LICENSE
jobmanager-0.4.8.dist-info/METADATA
jobmanager-0.4.8.dist-info/WHEEL
jobmanager-0.4.8.dist-info/RECORD
