Metadata-Version: 2.1
Name: jobmanager
Version: 0.4.8
Summary: a facility for distributed computing
Home-page: https://github.com/cimatosa/jobmanager
License: MIT
Keywords: multiprocessing,queue,parallel,distributed,computing,progress,manager,job,persistent data,scheduler
Author: Richard Hartmann
Requires-Python: >=3.9,<4.0
Classifier: Intended Audience :: Science/Research
Classifier: License :: OSI Approved :: MIT License
Classifier: Operating System :: OS Independent
Classifier: Programming Language :: Python :: 3
Classifier: Programming Language :: Python :: 3.9
Classifier: Programming Language :: Python :: 3.10
Classifier: Programming Language :: Python :: 3.11
Requires-Dist: binfootprint (>=1.2.0,<2.0.0)
Requires-Dist: numpy (>=1.24.1,<2.0.0)
Requires-Dist: progression (>=0.2.0,<0.3.0)
Requires-Dist: scipy (>=1.8.1,<2.0.0)
Requires-Dist: threadpoolctl (==3.1.0)
Project-URL: Repository, https://github.com/cimatosa/jobmanager
